{"cameraMode":{"drawMode":0,"name":"Shaded","section":"Shading Mode"},"sceneLighting":true,"audioPlay":false,"sceneViewState":{"m_AlwaysRefresh":false,"showFog":true,"showSkybox":true,"showFlares":true,"showImageEffects":true,"showParticleSystems":true,"showVisualEffectGraphs":true,"m_FxEnabled":true},"in2DMode":false,"pivot":{"x":8.32220458984375,"y":8.06738567352295,"z":-7.47476863861084},"rotation":{"x":0.3489658236503601,"y":-0.28964537382125857,"z":0.11438364535570145,"w":0.883975625038147},"size":1.991201639175415,"orthographic":false}